pslab/99-pslab.rules
pslab/__init__.py
pslab/cli.py
pslab/peripherals.py
pslab/protocol.py
pslab/sciencelab.py
pslab/serial_handler.py
pslab/bus/__init__.py
pslab/bus/busio.py
pslab/bus/i2c.py
pslab/bus/spi.py
pslab/bus/uart.py
pslab/connection/__init__.py
pslab/connection/_serial.py
pslab/connection/connection.py
pslab/connection/wlan.py
pslab/external/AD7718_class.py
pslab/external/AD9833.py
pslab/external/ADS1115.py
pslab/external/BH1750.py
pslab/external/ComplementaryFilter.py
pslab/external/HMC5883L.py
pslab/external/Kalman.py
pslab/external/MF522.py
pslab/external/MLX90614.py
pslab/external/MPU6050.py
pslab/external/MPU925x.py
pslab/external/SHT21.py
pslab/external/Sx1276.py
pslab/external/TSL2561.py
pslab/external/__init__.py
pslab/external/bmp180.py
pslab/external/ccs811.py
pslab/external/display.py
pslab/external/gas_sensor.py
pslab/external/hcsr04.py
pslab/external/motor.py
pslab/external/sensorlist.py
pslab/external/ssd1306_gfx.json
pslab/external/supported.py
pslab/external/tcd1304.py
pslab/instrument/__init__.py
pslab/instrument/analog.py
pslab/instrument/buffer.py
pslab/instrument/digital.py
pslab/instrument/logic_analyzer.py
pslab/instrument/multimeter.py
pslab/instrument/oscilloscope.py
pslab/instrument/power_supply.py
pslab/instrument/waveform_generator.py
pslab-4.0.1.dist-info/entry_points.txt
pslab-4.0.1.dist-info/licenses/LICENSE
pslab-4.0.1.dist-info/WHEEL
pslab-4.0.1.dist-info/METADATA
pslab-4.0.1.dist-info/RECORD
