Metadata-Version: 2.4
Name: pslab
Version: 4.0.1
Summary: Pocket Science Lab by FOSSASIA.
Author-email: FOSSASIA PSLab Developers <pslab-fossasia@googlegroups.com>
Requires-Python: >=3.8
Classifier: Programming Language :: Python :: 3
Classifier: License :: OSI Approved :: GNU General Public License v3 (GPLv3)
Classifier: Operating System :: OS Independent
Classifier: Development Status :: 5 - Production/Stable
License-File: LICENSE
Requires-Dist: pyserial
Requires-Dist: numpy
Requires-Dist: scipy
Requires-Dist: mcbootflash >= 8.0.0
Project-URL: Home, https://pslab.io/
